takumi_client/__init__.py
takumi_client/hosts.py
takumi_client/pool.py
takumi_client-0.1.3.dist-info/top_level.txt
takumi_client-0.1.3.dist-info/METADATA
takumi_client-0.1.3.dist-info/DESCRIPTION.rst
takumi_client-0.1.3.dist-info/metadata.json
takumi_client-0.1.3.dist-info/WHEEL
takumi_client-0.1.3.dist-info/RECORD
