Metadata-Version: 2.0
Name: takumi-client
Version: 0.1.3
Summary: Thrift client pool for Takumi
Home-page: https://github.com/elemepi/takumi-client
Author: Eleme Lab
Author-email: imaralla@icloud.com
License: UNKNOWN
Platform: UNKNOWN
Requires-Dist: takumi-ext
Requires-Dist: takumi-config
Requires-Dist: takumi-thrift
Requires-Dist: thriftpy
Requires-Dist: schema
